README.rst
setup.py
curve/__init__.py
curve/data_structure.py
curve/fitting.py
pyhardware/__init__.py
pyhardware.egg-info/PKG-INFO
pyhardware.egg-info/SOURCES.txt
pyhardware.egg-info/dependency_links.txt
pyhardware.egg-info/top_level.txt
pyhardware/config/__init__.py
pyhardware/config/connected_instruments.py
pyhardware/config/pyinstruments_config.py
pyhardware/config/gui/__init__.py
pyhardware/config/gui/pyinstruments_config_gui.py
pyhardware/config/gui/pytreewidget.py
pyhardware/config/gui/pytreewidgetold.py
pyhardware/drivers/__init__.py
pyhardware/drivers/driver.py
pyhardware/drivers/multiple_choice.py
pyhardware/drivers/ivi/__init__.py
pyhardware/drivers/ivi/agna.py
pyhardware/drivers/ivi/ividriver.py
pyhardware/drivers/ivi/scope.py
pyhardware/drivers/ivi/specan.py
pyhardware/drivers/serial/__init__.py
pyhardware/drivers/serial/agilent34401a.py
pyhardware/drivers/serial/arduino.py
pyhardware/drivers/serial/keithley2000.py
pyhardware/drivers/serial/serial_driver.py
pyhardware/drivers/visa/__init__.py
pyhardware/drivers/visa/afg.py
pyhardware/drivers/visa/tds2024b.py
pyhardware/drivers/visa/visa_driver.py
pyhardware/utils/__init__.py
pyhardware/utils/class_utils.py
pyhardware/utils/gui_fetch_utils.py
pyhardware/utils/conf_xml/__init__.py
pyhardware/utils/conf_xml/conf.py
pyhardware/utils/guiwrappersutils/__init__.py
pyhardware/utils/guiwrappersutils/guiwrapper.py
pyhardware/config/__init__.py
pyhardware/config/connected_instruments.py
pyhardware/config/pyinstruments_config.py
pyhardware/config/gui/__init__.py
pyhardware/config/gui/pyinstruments_config_gui.py
pyhardware/config/gui/pytreewidget.py
pyhardware/config/gui/pytreewidgetold.py
pyhardware/drivers/__init__.py
pyhardware/drivers/driver.py
pyhardware/drivers/multiple_choice.py
pyhardware/drivers/ivi/__init__.py
pyhardware/drivers/ivi/agna.py
pyhardware/drivers/ivi/ividriver.py
pyhardware/drivers/ivi/scope.py
pyhardware/drivers/ivi/specan.py
pyhardware/drivers/serial/__init__.py
pyhardware/drivers/serial/agilent34401a.py
pyhardware/drivers/serial/arduino.py
pyhardware/drivers/serial/keithley2000.py
pyhardware/drivers/serial/serial_driver.py
